[
    {
      "Image": "https://randomuser.me/api/portraits/men/52.jpg",
      "PNR": "PQ005XY01",
      "airlineNumber": "PQ005",
      "age": 25,
      "contactNumber": 9811954293,
      "firstName": "Dolores",
      "id": 1,
      "infants": true,
      "lastName": "Vincent",
      "luggage": "25kg",
      "meal": "Veg",
      "payPerView": "Hollywood",
      "seatNo": "A1",
      "address": "124 street Random city Popular Country",
      "passport": "XYZ123AB31",
      "dob": "1999-08-18",
      "inFlightShopping": true,
      "wheelChair": false
    },
    {
      "id": 2,
      "firstName": "William",
      "airlineNumber": "PQ005",
      "lastName": "Volonte",
      "age": 22,
      "contactNumber": 9811954203,
      "infants": true,
      "wheelChair": false,
      "PNR": "PQ005XY02",
      "seatNo": "A3",
      "Image": "https://randomuser.me/api/portraits/men/82.jpg",
      "meal": "Veg",
      "luggage": "25kg",
      "payPerView": "Bollywood",
      "address": "124 street Random city Popular Country",
      "passport": "XYZ123AB32",
      "dob": "1999-08-18"
    },
    {
      "id": 3,
      "firstName": "Lyda",
      "airlineNumber": "PQ005",
      "lastName": "Pead",
      "age": 38,
      "contactNumber": 9811954215,
      "infants": false,
      "wheelChair": false,
      "PNR": "PQ005XY03",
      "seatNo": "C2",
      "Image": "https://randomuser.me/api/portraits/women/13.jpg",
      "meal": "Non-Veg",
      "luggage": "15kg",
      "payPerView": "Bollywood",
      "address": "124 street Random city Popular Country",
      "passport": "XYZ123AB32",
      "dob": "1999-08-18"
    },
    {
      "id": 4,
      "firstName": "Bambi",
      "airlineNumber": "PQ005",
      "lastName": "Mussared",
      "age": 17,
      "contactNumber": 9811954217,
      "infants": true,
      "wheelChair": false,
      "PNR": "PQ005XY04",
      "seatNo": "C1",
      "Image": "https://randomuser.me/api/portraits/women/55.jpg",
      "meal": "Veg",
      "luggage": "40kg",
      "payPerView": "Bollywood",
      "address": "124 street Random city Popular Country",
      "passport": "XYZ123AB33",
      "dob": "1999-08-18"
    },
    {
      "id": 5,
      "airlineNumber": "PQ005",
      "firstName": "Alison",
      "lastName": "McGuffie",
      "age": 1,
      "contactNumber": 9811954258,
      "infants": true,
      "wheelChair": true,
      "PNR": "PQ005XY05",
      "seatNo": "F1",
      "Image": "https://randomuser.me/api/portraits/women/46.jpg",
      "luggage": "25kg",
      "meal": "Special Meal",
      "payPerView": "Hollywood",
      "address": "124 street Random city Popular Country",
      "passport": "XYZ123AB34",
      "dob": "1999-08-18",
      "inFlightShopping": false
    },
    {
      "id": 6,
      "airlineNumber": "PQ005",
      "firstName": "Harlie",
      "lastName": "Boucher",
      "age": 12,
      "contactNumber": 9811954254,
      "infants": false,
      "wheelChair": true,
      "PNR": "PQ005XY06",
      "seatNo": "D1",
      "Image": "https://randomuser.me/api/portraits/women/47.jpg",
      "luggage": "15kg",
      "meal": "Veg",
      "payPerView": "Bollywood",
      "address": "124 street Random city Popular Country",
      "passport": "XYZ123AB35",
      "dob": "1999-08-18",
      "inFlightShopping": false
    },
    {
      "id": 7,
      "airlineNumber": "PQ005",
      "firstName": "Cly",
      "lastName": "Withrington",
      "age": 40,
      "contactNumber": 9811954258,
      "infants": false,
      "wheelChair": false,
      "PNR": "PQ005XY07",
      "seatNo": "D5",
      "Image": "https://randomuser.me/api/portraits/women/48.jpg",
      "luggage": "25kg",
      "meal": "Veg",
      "payPerView": "Tollywood",
      "address": "124 street Random city Popular Country",
      "passport": "XYZ123AB36",
      "dob": "1999-08-18"
    },
    {
      "id": 8,
      "airlineNumber": "PQ005",
      "firstName": "Carlita",
      "lastName": "Izzard",
      "age": 39,
      "contactNumber": 9811954268,
      "infants": false,
      "wheelChair": false,
      "PNR": "PQ005XY08",
      "seatNo": "D6",
      "Image": "https://randomuser.me/api/portraits/men/49.jpg",
      "luggage": "25kg",
      "payPerView": "Hollywood",
      "address": "124 street Random city Popular Country",
      "passport": "XYZ123AB37",
      "dob": "1999-08-18"
    },
    {
      "id": "9",
      "PNR": "PQ005XY9",
      "airlineNumber": "PQ005",
      "firstName": "D2",
      "lastName": " J1",
      "contactNumber": "9090",
      "address": "wrad -12\nJain Mohalla",
      "passport": "IO90",
      "dob": "2019-08-29",
      "luggage": "",
      "meal": "",
      "payPerView": "",
      "inFlightShopping": false,
      "infants": false,
      "wheelChair": false
    },
    {
      "id": "10",
      "PNR": "PQ005XY10",
      "airlineNumber": "PQ005",
      "firstName": "dummy",
      "lastName": "2",
      "contactNumber": "90909090",
      "address": "wrad -12\nJain Mohalla",
      "passport": "JKJK9090",
      "dob": "2019-05-16",
      "luggage": "",
      "meal": "",
      "payPerView": "",
      "inFlightShopping": false,
      "infants": false,
      "wheelChair": false
    },
    {
      "id": "11",
      "PNR": "PQ005XY11",
      "airlineNumber": "PQ005",
      "firstName": "yaya",
      "lastName": "Tourey",
      "contactNumber": "90901212",
      "address": "wrad -12\nJain Mohalla",
      "passport": "AHJU789",
      "dob": "2019-12-06",
      "luggage": "25kg",
      "meal": "Special Meal",
      "payPerView": "Hollywood",
      "inFlightShopping": true,
      "seatNo": "B1",
      "infants": false,
      "wheelChair": false
    },
    {
      "id": "12",
      "PNR": "PQ005XY12",
      "airlineNumber": "PQ005",
      "firstName": "TEST ",
      "lastName": "USER",
      "contactNumber": "0099009900",
      "luggage": "",
      "meal": "",
      "payPerView": "",
      "inFlightShopping": false,
      "seatNo": "F7",
      "infants": false,
      "wheelChair": false,
      "passport": ""
    }
]